<?xml version="1.0" encoding="UTF-8"?>
<!DOCTYPE item PUBLIC "-//UPS//DTD MELCDL-REV1//EN" "melcdl.dtd">
<item chapnbr="26" chg="U" itemnbr="2-2" key="UPS747MEL20070815102818" revdate="20090824" revnbr="7" sectnbr="11">
<title>Engine Overheat Detection System &ndash; Flight Deck Test System</title>
<dispcond attr-rev="NO" category="C" maintenance="YES" nbrins="1"
nbrreq="0" btb="YES">
<remarks>
<para>May be inoperative provided an alternate procedure is established
to assure system integrity.</para>
</remarks>
<placard>
<para>Placard near FIRE/OVHT TEST Switch on P5 pilot&rsquo;s overhead
panel: "TEST FEATURE INOP". Enter Item in Aircraft Deferred Item Log.</para>
</placard>
<maintenance key="UPS747MEL20070815102819">
<para>The following CMC ground test procedure may be used to assure
system integrity:</para>
<numlist>
<numlitem><para>Close circuit breakers (AMM 26-11-00/501).</para>
</numlitem>
<numlitem><para>Set either of the following switches to ENABLE position:</para>
<numlist>
<numlitem><para>S2089 Ground Test Enable Switch (P461).</para>
</numlitem>
<numlitem><para>S2090 Remote Test Enable Switch (RCDU) at STA 400
bulkhead in the left main equipment center located near upper left
side of ladder. </para></numlitem>
</numlist>
</numlitem>
<numlitem><para>Set the CDU to the CMC main menu.</para></numlitem>
<numlitem><para>Press LINE SELECT key for GROUND TEST.</para></numlitem>
<numlitem><para>When screen displays ATA name and chapter, select
26 FIRE PROTECTION SYSTEM.</para></numlitem>
<numlitem><para>To initiate test, press LINE SELECT key for FIRE/OVHT
TEST. </para></numlitem>
<numlitem><para>The TEST IN PROGRESS indication will be displayed
for the duration of the test.</para></numlitem>
<numlitem><para>When the test is done, the CDU will display TEST PASSED
or FIRE TEST FAIL.</para>
<note><para>The indication FIRE TEST FAIL may appear as a result of
circuit breaker being open on related fire/overheat detection system.</para>
</note>
<numlist>
<numlitem><para>If the indication is TEST PASSED, the test is finished
and system integrity is verified.</para></numlitem>
<numlitem><para>If the indication is FIRE TEST FAIL, verify that the
following CMC messages do not appear on CDU:</para>
<table frame="none">
<tgroup align="center" cols="2">
<colspec colname="col1" colsep="0" colwidth="247.20pt"/>
<colspec align="center" char="" charoff="50" colname="COLSPEC2"
colsep="0" colwidth="262.80pt"/>
<tbody>
<row>
<entry>
<para>ENG-1 NACELLE OVERHEAT-1 FAIL</para>
<para>ENG-2 NACELLE OVERHEAT-1 FAIL</para>
<para>ENG-3 NACELLE OVERHEAT-1 FAIL</para>
<para>ENG-4 NACELLE OVERHEAT-1 FAIL</para>
</entry>
<entry>
<para>ENG-1 NACELLE OVERHEAT-B FAIL</para>
<para>ENG-2 NACELLE OVERHEAT-B FAIL</para>
<para>ENG-3 NACELLE OVERHEAT-B FAIL</para>
<para>ENG-4 NACELLE OVERHEAT-B FAIL</para>
</entry>
</row>
</tbody>
</tgroup>
</table>
</numlitem>
</numlist>
</numlitem>
<numlitem><para>If CMC fault messages appear, seek corrective action.
Note that dispatch is allowed with one loop per engine inoperative.</para>
</numlitem>
</numlist>
</maintenance>
</dispcond>
</item>
