<?xml version="1.0" encoding="UTF-8"?>
<!DOCTYPE item PUBLIC "-//UPS//DTD MELCDL-REV1//EN" "melcdl.dtd">
<item chapnbr="21" chg="U" itemnbr="1-2" key="UPS-757-MEL-00000161" revdate="20100423" revnbr="68" sectnbr="53">
<title>Ram Air Inlet/Exhaust Door Systems &ndash; All Cargo Configuration</title>
<dispcond btb="NO" category="C" maintenance="YES" nbrins="2" nbrreq="1"
operation="YES">
<remarks>
<para>One may be inoperative in any position provided associated pack
is considered inoperative. </para>
<!--Per C.R.#4381 Bill Bombatch 3/9/10 Considered Inop Item-->
<note><para>Additional deferral required &ndash; Air Conditioning
Packs.</para></note>
</remarks>
<operation key="UPS-757-MEL-00000162">
<numlist>
<numlitem><para>With one pack inoperative, limit altitude to FL350
or below.</para></numlitem>
</numlist>
<note><para>With an air conditioning pack inoperative or OFF, isolation
valve closed, and anti-ice OFF, a BLEED OFF Light may illuminate during
takeoff power application. Under these conditions, the PRSOV is regulating
air pressure to a point where the valve angle is small enough to activate
the light switch. As engine power, and thus air pressure, is reduced
the valve angle opens slightly and the BLEED OFF Light extinguishes.</para>
</note>
</operation>
<limitation key="UPS-757-MEL-00000164">
<numlist>
<numlitem><para>Limit flight altitude to FL350 or below.</para>
</numlitem>
</numlist>
</limitation>
<placard>
<para>Placard affected Pack Control Selector "RAM AIR INLET/EX DOOR
INOP" and enter item in Aircraft Deferred Item Log.</para>
</placard>
<maintenance key="UPS757MELCDL20080528094458">
<title>Ram Air Inlet/Exhaust Door Systems</title>
<para>Doors In Any Other Position (Affected Pack Deactivated):</para>
<note><para>Exit area must be greater than inlet area to prevent noise
and vibration due to possible adverse pressure gradient.</para>
<numlist>
<numlitem><para>Rotate pack control selector to OFF. Verify that PACK
OFF light comes on.</para></numlitem>
<numlitem><para>Open and collar applicable L or R PACK FLOW CONTROL
circuit breaker on the P11 overhead panel. For aircraft with exhaust
doors, if exit area is not clearly greater than inlet area proceed
with step 3 or 4. </para></numlitem>
<numlitem><para>If exhaust door is operative:</para>
<numlist>
<numlitem><para>Verify that the Ram Air Exhaust Door is in the full
open position.</para></numlitem>
<numlitem><para>Disconnect, cap and stow Electrical Connector for
Exhaust Door Actuator. </para></numlitem>
</numlist>
</numlitem>
<numlitem><para>If Exhaust Door is inoperative - not full open:</para>
<numlist>
<numlitem><para>Remove Exhaust Door Actuator (AMM 21-53-04).</para>
</numlitem>
<numlitem><para>Fabricate Actuator Link 11.1 inch long with rod ends
compatible with door actuator fittings.</para></numlitem>
<numlitem><para>Position door to full open position and install actuator
link in place of Ram Air Actuator.</para></numlitem>
</numlist>
</numlitem>
<numlitem><para>For Left Ram Air Inlet/Exhaust Door System inoperative,
close the L PACK FLOW CONTROL circuit breaker.</para></numlitem>
<numlitem><para>Notify dispatch that (left or right) pack is inoperative
and flight will be limited to FL350 or below.</para></numlitem>
</numlist>
</note>
<graphic chapnbr="21" chg="U" key="UPS757MELCDL20080624142832"
revdate="20080924" revnbr="65" sectnbr="53">
<sheet chg="U" gnbr="DMP_CH_21_Page_52" key="UPS757MELCDL20080624142959"
revdate="20080924" revnbr="65" sheetnbr="001">
<title>RAM AIR EXHAUST DOOR OPEN POSITION RAM AIR INLET/EXHAUST DOOR
INSTALLATION</title>
</sheet>
</graphic>
<graphic chapnbr="21" chg="U" key="UPS757MELCDL20080624143610"
revdate="20080924" revnbr="65" sectnbr="53">
<sheet chg="U" gnbr="DMP_CH_21_Page_6" key="UPS757MELCDL20080624143708"
revdate="20080924" revnbr="65" sheetnbr="001">
<title>INLET/EXHAUST DOOR ACTUATOR LINK (A21007-2)</title>
</sheet>
</graphic>
</maintenance>
</dispcond>
</item>
