<?xml version="1.0" encoding="UTF-8"?>
<!DOCTYPE item PUBLIC "-//UPS//DTD MELCDL-REV1//EN" "melcdl.dtd">
<item chapnbr="34" chg="U" itemnbr="5-1" key="UPS-MEL-757-34220501FDK" revdate="20090814" revnbr="66" sectnbr="22">
<title>Electronic Flight Instrument System (EFIS) Symbol Generators</title>
<dispcond category="C" downgrade="CATEGORY 3a" maintenance="YES"
nbrins="3" nbrreq="2" operation="NO">
<remarks>
<para>Except for ER operations, one may be inoperative provided symbol
generator isolation is verified once each flight day.</para>
<note><para>Operative symbol generators must be associated with operative
IRS, radio altimeters and ILS receivers.</para></note>
</remarks>
<operation key="UPS-MEL-757-35220501OPSFDK">
<note><para>One EFIS system required at each pilot station. Instrument
source selections must be made from separate sources.</para></note>
</operation>
<limitation key="UPS-MEL-757-35220501LIMFDK">
<numlist>
<numlitem><para>Downgrade aircraft category dispatch status to CAT
3a.</para></numlitem>
</numlist>
</limitation>
<placard>
<para>If Left or Right Symbol Generator is inoperative, placard L
(R) EFI Source Select switch "L (R) EFI NORM INOP" and enter item
in Aircraft Deferred Item Log.</para>
<para>If Center Symbol Generator inoperative, placard both EFI Source
Select switches "EFI ALTN INOP" and enter item in Aircraft Deferred
Item Log.</para>
</placard>
<maintenance key="UPS-MEL-757-34220501MANFDK">
<note><para>The repetitive inspection required when this item is inoperative
must be documented in the Aircraft Logbook at the prescribed intervals.
(Refer to GMM, Chapter 3, Section 6.)</para></note>
<para>Deferral for this item requires downgrading to the status indicated
in the A/C STATUS DISPATCH column below.</para>
<table>
<tgroup cols="3">
<colspec colname="col1" colwidth="158.50pt"/>
<colspec colname="col2" colwidth="158.50pt"/>
<colspec colname="col3" colwidth="159.31pt"/>
<thead>
<row>
<entry align="center" valign="top">
<para>INOP</para>
<para>POSITION</para>
</entry>
<entry align="center" valign="top">
<para>NUMBER</para>
<para>INOP</para>
</entry>
<entry align="center" valign="top">
<para>A/C STATUS</para>
<para>DISPATCH</para>
</entry>
</row>
</thead>
<tbody>
<row>
<entry align="center">
<para>Any</para>
</entry>
<entry align="center">
<para>1</para>
</entry>
<entry align="center">
<para>CAT 3a</para>
</entry>
</row>
</tbody>
</tgroup>
</table>
<para>If Left Symbol Generator inoperative, select ALTN on Captain's
EFI source select. If Right Symbol Generator inoperative, select ALTN
on F/O's EFI source select.</para>
<para><emphasis role="bold"><emphasis role="underline">Center EFIS
Symbol Generator Inoperative:</emphasis></emphasis></para>
<para>Ensure the Captain and First Officer are utilizing different
Symbol Generators by performing the following:</para>
<para>With both L and R EFI switches in NORM, place the Captain&rsquo;s
EFIS control panel in the VOR mode and the First Officer&rsquo;s EFIS
control panel in the ILS mode. Observe that the <emphasis
role="underline">VOR L</emphasis> is annunciated on the Captain&rsquo;s
HSI.</para>
<para><emphasis role="bold"><emphasis role="underline">Left EFIS Symbol
Generator Inoperative:</emphasis></emphasis></para>
<para>Ensure the Captain and First Officer are utilizing different
Symbol Generators by performing the following: With Left EFI switch
in ALTN and the Right EFI switch in NORM, place the First Officer&rsquo;s
EFIS control panel in the VOR mode and the Captain&rsquo;s EFIS control
panel in the ILS mode. Observe that the <emphasis role="underline"
>VOR R</emphasis> is annunciated on the First Officer&rsquo;s HSI.</para>
<para><emphasis role="bold"><emphasis role="underline">Right EFIS
Symbol Generator Inoperative:</emphasis></emphasis></para>
<para>Ensure the Captain and First Officer are utilizing different
Symbol Generators by performing the following: With Right EFI switch
in ALTN and the Left EFI switch in NORM, place the Captain&rsquo;s
EFIS control panel in the VOR mode and the First Officer&rsquo;s EFIS
control panel in the ILS mode. Observe that the <emphasis
role="underline">VOR L</emphasis> is annunciated on the Captain&rsquo;s
HSI.</para>
</maintenance>
</dispcond>
</item>
