<?xml version="1.0" encoding="UTF-8"?>
<!DOCTYPE item PUBLIC "-//UPS//DTD MELCDL-REV1//EN" "melcdl.dtd">
<item chapnbr="36" chg="U" itemnbr="4" key="UPS-757-MEL-00001128" revdate="20080924" revnbr="65" sectnbr="22">
<title>Bleed ISLN Valve Light</title>
<dispcond btb="NO" category="C" maintenance="NO" nbrins="1" nbrreq="0"
operation="YES">
<remarks>
<para>May be inoperative provided both duct pressure indicators are
operative. </para>
</remarks>
<operation key="UPS-757-MEL-00001129">
<numlist>
<numlitem><para>If proper operation of the isolation valve is in question,
refer to the Duct Pressure Indications.</para></numlitem>
</numlist>
</operation>
<placard>
<para>Placard near the Bleed Isolation Valve Light "LIGHT INOP" and
enter item in Aircraft Deferred Item Log.</para>
</placard>
</dispcond>
</item>
