<?xml version="1.0" encoding="UTF-8"?>
<!DOCTYPE item PUBLIC "-//UPS//DTD MELCDL-REV1//EN" "melcdl.dtd">
<item chapnbr="30" chg="U" itemnbr="1-0-1" key="UPS-757-MEL-00000958" revdate="20091120" revnbr="67" sectnbr="33">
<title>Temperature (TAT) Probe Heater Systems</title>
<dispcond btb="NO" category="C" downgrade="CATEGORY 1" maintenance="NO"
nbrins="1" nbrreq="0" operation="YES">
<remarks>
<para>Except for ER operations beyond 120 minutes, may be inoperative
provided:</para>
<numlist>
<numlitem><para>Remaining probe heater indicating systems for operative
probe heaters are operative, and</para></numlitem>
<numlitem><para>Aircraft is not operated in known or forecast icing
conditions. </para></numlitem>
</numlist>
</remarks>
<operation key="UPS-757-MEL-00000959">
<numlist>
<numlitem><para>No flight in known or forecast icing conditions.</para>
</numlitem>
<numlitem><para>Thrust Management System will be unavailable.</para>
</numlitem>
</numlist>
<note><para>When the TAT heater system is inoperative, the TMC considers
the temperature from TAT to be invalid and disconnects Autothrottle.</para>
</note>
</operation>
<limitation key="UPS-757-MEL-JDM001234957">
<numlist>
<numlitem><para>Downgrade aircraft dispatch category status to CAT
1.</para></numlitem>
<numlitem><para>Operations in known or forecast icing conditions prohibited. </para>
</numlitem>
</numlist>
</limitation>
<placard>
<para>Placard TAT Light on Overhead Panel &ldquo;HEAT INOP&rdquo;
and enter item in Aircraft Deferred Item Log.</para>
</placard>
<maintenance key="UPS-757-MEL-00000960">
<para>Deferral of this item requires downgrading to the status indicated
in the A/C STATUS DISPATCH column below.</para>
<table>
<tgroup align="center" cols="3">
<colspec colname="COLSPEC0" colwidth="1.06*"/>
<colspec colname="col1" colwidth="1.05*"/>
<colspec colname="col2" colwidth="1.03*"/>
<thead>
<row>
<entry valign="top">
<para><emphasis role="bold">INOP POSITION</emphasis></para>
</entry>
<entry valign="top">
<para><emphasis role="bold">NUMBER INOP</emphasis></para>
</entry>
<entry valign="top">
<para><emphasis role="bold">A/C STATUS DISPATCH</emphasis></para>
</entry>
</row>
</thead>
<tbody>
<row>
<entry>
<para>&ndash;</para>
</entry>
<entry>
<para>1</para>
</entry>
<entry>
<para>CAT 1</para>
</entry>
</row>
</tbody>
</tgroup>
</table>
</maintenance>
</dispcond>
</item>
