<?xml version="1.0" encoding="UTF-8"?>
<!DOCTYPE item PUBLIC "-//UPS//DTD MELCDL-REV1//EN" "melcdl.dtd">
<item chapnbr="34" chg="U" itemnbr="3-1" key="UPS-MEL-757-3422311LFDK" revdate="20080924" revnbr="65" sectnbr="22">
<title>Radio Distance Magnetic Indicators (RDMI) &ndash; Right Inoperative</title>
<dispcond category="C" nbrins="2" nbrreq="1">
<remarks>
<para>Right may be inoperative. </para>
</remarks>
<placard>
<para>Placard Right Magnetic Indicator "INOP" and enter item in Aircraft
Deferred Item Log.</para>
</placard>
</dispcond>
</item>
