<?xml version="1.0" encoding="UTF-8"?>
<!DOCTYPE item PUBLIC "-//UPS//DTD MELCDL-REV1//EN" "melcdl.dtd">
<item chapnbr="29" chg="U" itemnbr="2-3" key="UPS757MELCDL20080609115245" revdate="20080924" revnbr="65" sectnbr="31">
<title>Pump Low PRESS Indication Systems &ndash; Center Electric Pump
Indication Systems</title>
<dispcond category="C" nbrins="2" nbrreq="1">
<remarks>
<para>One may be inoperative provided associated pump is selected
OFF.</para>
</remarks>
<placard>
<para>Placard affected Hydraulic Pump Low PRESS light(s) on Hydraulic
Control panel "INOP" and enter item in Aircraft Deferred Item Log.</para>
</placard>
</dispcond>
</item>
